datarobot_asgi_middleware/__init__.py
datarobot_asgi_middleware/_version.py
datarobot_asgi_middleware-0.2.0.dist-info/METADATA
datarobot_asgi_middleware-0.2.0.dist-info/WHEEL
datarobot_asgi_middleware-0.2.0.dist-info/licenses/AUTHORS
datarobot_asgi_middleware-0.2.0.dist-info/licenses/LICENSE
datarobot_asgi_middleware-0.2.0.dist-info/RECORD
