Metadata-Version: 2.4
Name: datarobot-asgi-middleware
Version: 0.2.0
Summary: A FastAPI/ASGI middleware to simplify development of FastAPI apps on DataRobot
Maintainer-email: DataRobot <oss-community-management@datarobot.com>
License-File: AUTHORS
License-File: LICENSE
Requires-Python: >=3.9
Requires-Dist: starlette
